openml_tensorflow/__init__.py
openml_tensorflow/config.py
openml_tensorflow/extension.py
openml_tensorflow-1.0.0.dist-info/LICENSE
openml_tensorflow-1.0.0.dist-info/METADATA
openml_tensorflow-1.0.0.dist-info/WHEEL
openml_tensorflow-1.0.0.dist-info/top_level.txt
openml_tensorflow-1.0.0.dist-info/RECORD
