Metadata-Version: 2.1
Name: openml-tensorflow
Version: 1.0.0
Summary: Tensorflow extension for Openml python API
Home-page: http://openml.org/
Author: Prabhant Singh, Taniya Das
Author-email: prabhantsingh@gmail.com, taniyatd30@gmail.com
Maintainer: Taniya Das
Maintainer-email: taniyatd30@gmail.com
License: BSD 3-clause
Project-URL: Documentation, https://openml.github.io/openml-tensorflow/
Project-URL: Source Code, https://github.com/openml/openml-tensorflow
Classifier: Intended Audience :: Science/Research
Classifier: Intended Audience :: Developers
Classifier: License :: OSI Approved :: BSD License
Classifier: Programming Language :: Python
Classifier: Topic :: Software Development
Classifier: Topic :: Scientific/Engineering
Classifier: Operating System :: POSIX
Classifier: Operating System :: Unix
Classifier: Operating System :: MacOS
Classifier: Programming Language :: Python :: 3
Classifier: Programming Language :: Python :: 3.5
Classifier: Programming Language :: Python :: 3.6
Classifier: Programming Language :: Python :: 3.7
Classifier: Programming Language :: Python :: 3.8
Classifier: Programming Language :: Python :: 3.9
Classifier: Programming Language :: Python :: 3.10
Classifier: Programming Language :: Python :: 3.11
Classifier: Programming Language :: Python :: 3.12
Requires-Python: >=3.5
License-File: LICENSE
Requires-Dist: openml
Requires-Dist: tensorflow <2.16.0,>=2.0
Requires-Dist: tf2onnx
Requires-Dist: dill
Requires-Dist: pillow
